odoo/addons/mrp_viewer/__init__.py
odoo/addons/mrp_viewer/__manifest__.py
odoo/addons/mrp_viewer/security/ir.model.access.csv
odoo/addons/mrp_viewer/security/mrp_security.xml
odoo/addons/mrp_viewer/static/description/icon.png
odoo/addons/mrp_viewer/views/mrp.xml
odoo12_addon_mrp_viewer-12.0.1.0.0.99.dev2.dist-info/METADATA
odoo12_addon_mrp_viewer-12.0.1.0.0.99.dev2.dist-info/WHEEL
odoo12_addon_mrp_viewer-12.0.1.0.0.99.dev2.dist-info/top_level.txt
odoo12_addon_mrp_viewer-12.0.1.0.0.99.dev2.dist-info/RECORD
